pandas_object/__init__.py
pandas_object/convert.py
pandas_object-0.1.3.dist-info/WHEEL
pandas_object-0.1.3.dist-info/METADATA
pandas_object-0.1.3.dist-info/RECORD
