Metadata-Version: 2.1
Name: pandas-object
Version: 0.1.3
Summary: 
Author: dwpeng
Author-email: 1732889554@qq.com
Requires-Python: >=3,<4
Classifier: Programming Language :: Python :: 3
Classifier: Programming Language :: Python :: 3.4
Classifier: Programming Language :: Python :: 3.5
Classifier: Programming Language :: Python :: 3.6
Classifier: Programming Language :: Python :: 3.7
Classifier: Programming Language :: Python :: 3.8
Classifier: Programming Language :: Python :: 3.9
Classifier: Programming Language :: Python :: 3.10
Classifier: Programming Language :: Python :: 3.11
Requires-Dist: pandas
Requires-Dist: rich
